queen/__init__.py
queen/backup.py
queen/exceptions.py
queen/logs.py
queen/main.py
queen/parsing/__init__.py
queen/parsing/arguments.py
queen/parsing/config.py
queen/parsing/site.py
queen/plugins/__init__.py
queen/plugins/docker_volume.py
queen/plugins/mysql.py
queen/plugins/postgres.py
queen/processes.py
borg_queen-1.0.1.dist-info/METADATA
borg_queen-1.0.1.dist-info/WHEEL
borg_queen-1.0.1.dist-info/entry_points.txt
borg_queen-1.0.1.dist-info/RECORD
