Metadata-Version: 2.1
Name: borg-queen
Version: 1.0.1
Summary: Wrapper for Borg Backup.
Home-page: https://bitbucket.org/indev/queen/
License: ISC
Author: Indev
Author-email: admin@indevsoftware.io
Requires-Python: >=3.11,<4.0
Classifier: License :: OSI Approved
Classifier: Programming Language :: Python :: 3
Classifier: Programming Language :: Python :: 3.11
Classifier: Programming Language :: Python :: 3.12
Classifier: Programming Language :: Python :: 3.13
Requires-Dist: sentry-sdk (>=1.0.0,<2.0.0)
Requires-Dist: toml (>=0.10.2,<0.11.0)
